{
  "id": "emobilitaet",
  "title": "E-Mobilität",
  "subtitle": "Fakten zu Reichweite, Akkus, Kosten & Klimabilanz",
  "icon": "electric_car",
  "lastUpdated": "2026-03",
  "keyStats": [
    "2,03 Mio. BEV in Deutschland",
    ">190.000 öffentliche Ladepunkte",
    "19,1 % BEV-Marktanteil (2025)",
    "7 Argumente"
  ],
  "sourceNote": "Quellen: ICCT, ADAC, BMUKN, BDEW, Bundesnetzagentur, KBA, Fraunhofer ISI, Transport & Environment und EU-Batterieverordnung (Stand März 2026).",
  "sections": [
    {
      "id": "status-quo",
      "title": "Status Quo: E-Autos in Deutschland",
      "content": [
        {
          "type": "stat_grid",
          "items": [
            { "value": "2,03 Mio.", "label": "E-Autos (BEV)", "sublabel": "Bestand 1. Jan 2026 (KBA)" },
            { "value": ">190.000", "label": "Öffentl. Ladepunkte", "sublabel": "davon >48.000 Schnelllader (BNetzA)" },
            { "value": "19,1 %", "label": "BEV-Marktanteil", "sublabel": "Neuzulassungen 2025" }
          ],
          "sourceRefs": [3, 8]
        },
        {
          "type": "line_chart",
          "caption": "Marktanteil reiner E-Autos (BEV) an Neuzulassungen in Deutschland",
          "unit": "%",
          "items": [
            { "label": "2020", "value": 6.7 },
            { "label": "2021", "value": 13.6 },
            { "label": "2022", "value": 17.7 },
            { "label": "2023", "value": 18.4 },
            { "label": "2024", "value": 13.5 },
            { "label": "2025", "value": 19.1 }
          ],
          "sourceRefs": [3]
        },
        {
          "type": "fact",
          "text": "Nach dem Einbruch 2024 stieg der BEV-Anteil an den Neuzulassungen 2025 wieder auf 19,1 %. Gegenüber 2024 legte der BEV-Anteil damit wieder zu.",
          "highlight": true,
          "sourceRefs": [3]
        }
      ]
    },
    {
      "id": "klimabilanz",
      "title": "Klimabilanz: Der CO₂-Rucksack",
      "content": [
        {
          "type": "text",
          "text": "Ein E-Auto startet wegen der Batterieproduktion mit einem „CO₂-Rucksack“ ins Leben. Dieser wird im Fahrbetrieb abgebaut, da der E-Motor deutlich effizienter ist und der Strommix immer grüner wird.",
          "sourceRefs": [1, 5]
        },
        {
          "type": "stat_grid",
          "items": [
            { "value": "~17.000 km", "label": "Break-Even", "sublabel": "in Europa (ICCT 2025)", "color": "#00897b" },
            { "value": "-73 %", "label": "CO₂-Emissionen", "sublabel": "über Lebenszyklus (ICCT 2025)" }
          ],
          "sourceRefs": [1]
        },
        {
          "type": "fact",
          "text": "Laut ICCT (Juli 2025) verursachen 2025 in Europa verkaufte Batterie-Elektroautos über ihren Lebenszyklus rund 73 % weniger Treibhausgasemissionen als vergleichbare Benziner.",
          "highlight": true,
          "sourceRefs": [1]
        },
        {
          "type": "fact",
          "text": "Der CO₂-Rucksack aus der Produktion wird im Betrieb schrittweise ausgeglichen, weil E-Motoren effizienter sind und der Strommix weiter dekarbonisiert.",
          "sourceRefs": [1, 5]
        }
      ]
    },
    {
      "id": "kosten-tco",
      "title": "Kosten (TCO): Was ist unterm Strich günstiger?",
      "content": [
        {
          "type": "text",
          "text": "TCO (Total Cost of Ownership) beinhaltet Anschaffung, Wertverlust, Steuern, Versicherung, Wartung und Energiekosten (ADAC Autokostenrechner).",
          "sourceRefs": [2]
        },
        {
          "type": "comparison",
          "caption": "ADAC-TCO: Worauf es bei den Gesamtkosten ankommt",
          "items": [
            {
              "title": "Verbrenner",
              "color": "#546e7a",
              "rows": [
                { "label": "Kaufpreis", "value": "oft etwas niedriger" },
                { "label": "Energiekosten", "value": "abhängig von Kraftstoffpreisen" },
                { "label": "Kfz-Steuer", "value": "regelmäßig fällig" },
                { "label": "Wartung/Verschleiß", "value": "tendenziell höher" }
              ],
              "total": { "label": "Gesamtkosten", "value": "stark modellabhängig" }
            },
            {
              "title": "E-Auto (BEV)",
              "color": "#00897b",
              "rows": [
                { "label": "Kaufpreis", "value": "oft etwas höher" },
                { "label": "Energiekosten", "value": "abhängig vom Ladetarif" },
                { "label": "Kfz-Steuer", "value": "bis Ende 2030 befreit" },
                { "label": "Wartung/Verschleiß", "value": "tendenziell geringer" }
              ],
              "total": { "label": "Gesamtkosten", "value": "stark modellabhängig" }
            }
          ],
          "savings": "Entscheidend ist der Vergleich konkreter Modelle im ADAC-Autokostenrechner.",
          "sourceRefs": [2, 12]
        },
        {
          "type": "fact",
          "text": "Trotz oft höherem Listenpreis können E-Autos in der Gesamtkostenrechnung (TCO) je nach Modell, Nutzung und Ladekosten günstiger sein als vergleichbare Verbrenner.",
          "highlight": true,
          "sourceRefs": [2]
        }
      ]
    },
    {
      "id": "akkus-rohstoffe",
      "title": "Akkus: Lebensdauer, Rohstoffe & Recycling",
      "content": [
        {
          "type": "stat_grid",
          "items": [
            { "value": "90 %", "label": "Rückgewinnung", "sublabel": "ab Ende 2027 für Kobalt, Kupfer, Blei und Nickel" },
            { "value": "50 %", "label": "Lithium", "sublabel": "Rückgewinnungsziel bis Ende 2027, später 80 %" },
            { "value": "Second Life", "label": "Nachnutzung", "sublabel": "Fahrzeugbatterien können stationär weitergenutzt werden" }
          ]
        },
        {
          "type": "table",
          "headers": ["Fakt", "Erklärung"],
          "rows": [
            ["LFP-Technologie", "Lithium-Eisenphosphat-Akkus kommen ohne Kobalt und Nickel aus."],
            ["Recycling", "Die EU-Batterieverordnung schreibt ab Ende 2027 hohe Rückgewinnungsziele für zentrale Batterierohstoffe vor."],
            ["Second Life", "Ausgemusterte Auto-Akkus (mit <80% Kapazität) werden jahrelang als stationäre Stromspeicher weitergenutzt."]
          ]
        },
        {
          "type": "fact",
          "text": "Die Rohstofffrage ist real, aber Batterien sind reguliert: Hersteller reduzieren kritische Materialien, und die EU verschärft die Recyclingvorgaben deutlich.",
          "highlight": true,
          "sourceRefs": [7, 11]
        }
      ]
    },
    {
      "id": "stromnetz",
      "title": "Stromnetz: Droht der Blackout?",
      "content": [
        {
          "type": "stat_grid",
          "items": [
            { "value": "4,2 kW", "label": "Mindestleistung", "sublabel": "bei Dimmung nach § 14a EnWG" },
            { "value": "§ 14a EnWG", "label": "Regelung", "sublabel": "verhindert lokale Überlastung" },
            { "value": "smart laden", "label": "Praxis", "sublabel": "Engpässe werden lokal statt pauschal gemanagt" }
          ],
          "sourceRefs": [4]
        },
        {
          "type": "fact",
          "text": "Neue steuerbare Ladeeinrichtungen dürfen nicht pauschal wegen lokaler Engpässe abgelehnt werden. Im Engpassfall darf der Strombezug zeitweise reduziert werden, die Bundesnetzagentur schreibt dabei aber eine Mindestleistung von 4,2 kW vor.",
          "highlight": true,
          "sourceRefs": [4]
        },
        {
          "type": "text",
          "text": "Lokale Überlastungen werden durch intelligentes Laden gemanagt. Netzbetreiber dürfen Wallboxen im Engpassfall zeitweise dimmen, aber nicht vollständig abschalten.",
          "sourceRefs": [4]
        }
      ]
    },
    {
      "id": "efuels-wasserstoff",
      "title": "E-Fuels & Wasserstoff im PKW: Ein Effizienzproblem",
      "content": [
        {
          "type": "table",
          "caption": "Direkte Stromnutzung ist im Pkw am effizientesten",
          "headers": ["Antrieb", "Kernaussage"],
          "rows": [
            ["E-Auto (BEV)", "Direkte Nutzung von Strom im Fahrzeug ist am effizientesten."],
            ["Wasserstoff", "Zusätzliche Umwandlungsschritte kosten im Pkw viel Energie."],
            ["E-Fuels", "Sollten vor allem dort eingesetzt werden, wo Batterien kaum praktikabel sind."]
          ],
          "sourceRefs": [6]
        },
        {
          "type": "fact",
          "text": "Für Pkw ist die direkte Nutzung von Strom im Batterieauto deutlich effizienter als Wasserstoff oder E-Fuels.",
          "highlight": true,
          "sourceRefs": [6]
        },
        {
          "type": "text",
          "text": "E-Fuels und Wasserstoff sind wertvoll und werden vor allem in Sektoren gebraucht, die sich nur schwer direkt elektrifizieren lassen, etwa im Flugverkehr, in der Schifffahrt und in Teilen der Industrie. Im Pkw sind sie energetisch deutlich ineffizienter und meist nicht der sinnvolle Einsatz."
        }
      ]
    },
    {
      "id": "brandgefahr",
      "title": "Brandgefahr: Brennen E-Autos häufiger?",
      "content": [
        {
          "type": "fact",
          "text": "Elektroautos brennen laut BMUKN nicht häufiger als andere Fahrzeuge.",
          "highlight": true,
          "sourceRefs": [10]
        },
        {
          "type": "text",
          "text": "Ein brennendes Elektroauto ist laut BMUKN in thermischer Hinsicht nicht gefährlicher als ein brennendes Fahrzeug mit konventionellem Antrieb.",
          "sourceRefs": [10]
        },
        {
          "type": "text",
          "text": "Wenn ein E-Auto brennt, ist es oft aufwendiger zu löschen, weil der Akku gekühlt werden muss. Für Feuerwehren ist das ein bekanntes Einsatzszenario."
        }
      ]
    }
  ],
  "arguments": [
    {
      "id": "akku-kaputt",
      "claim": "Nach 3 bis 5 Jahren ist der Akku kaputt und ein neuer kostet 15.000 Euro.",
      "response": "Das ist so pauschal falsch. Moderne Traktionsbatterien sind auf lange Nutzung ausgelegt, Hersteller geben mehrjährige Garantien, und die Batterie ist normalerweise nicht schon nach wenigen Jahren am Ende. Entscheidend sind Fahrzeugmodell, Nutzung und Batterietyp.",
      "keywords": ["akku", "kaputt", "lebensdauer", "austausch", "garantie", "kosten"],
      "relatedSections": ["akkus-rohstoffe"]
    },
    {
      "id": "stromnetz-kollaps",
      "claim": "Wenn alle abends ihr E-Auto anstecken, bricht das Stromnetz zusammen.",
      "response": "Nein. Netzbetreiber dürfen neue steuerbare Ladeeinrichtungen nicht pauschal wegen lokaler Engpässe ablehnen. Im Engpassfall darf der Strombezug nach § 14a EnWG vorübergehend auf 4,2 kW reduziert werden; diese Mindestleistung muss laut Bundesnetzagentur immer verfügbar bleiben.",
      "keywords": ["stromnetz", "blackout", "zusammenbruch", "laden", "netz", "überlastung"],
      "relatedSections": ["stromnetz"]
    },
    {
      "id": "co2-rucksack",
      "claim": "Wegen der Batterieproduktion ist ein E-Auto klimaschädlicher als ein Diesel.",
      "response": "Falsch. Laut ICCT verursachen 2025 in Europa verkaufte Batterie-Elektroautos über ihren Lebenszyklus rund 73 % weniger Treibhausgasemissionen als vergleichbare Benziner. Der höhere CO₂-Fußabdruck der Produktion wird im Fahrbetrieb wieder ausgeglichen.",
      "keywords": ["klimaschädlich", "co2", "rucksack", "produktion", "diesel", "umwelt"],
      "relatedSections": ["klimabilanz"]
    },
    {
      "id": "kobalt-kinderarbeit",
      "claim": "Für E-Autos schuften Kinder im Kongo für Kobalt.",
      "response": "Die Probleme im Rohstoffabbau sind real und müssen ernst genommen werden. Gleichzeitig sinkt der Einsatz kritischer Materialien bei manchen Batterietypen, LFP-Akkus kommen ohne Kobalt und Nickel aus, und die EU verschärft die Recyclingvorgaben für Batterierohstoffe deutlich.",
      "keywords": ["kobalt", "kinderarbeit", "kongo", "rohstoffe", "ausbeutung"],
      "relatedSections": ["akkus-rohstoffe"]
    },
    {
      "id": "wasserstoff-zukunft",
      "claim": "Batterien sind nur eine Brückentechnologie, Wasserstoff und E-Fuels sind die Zukunft.",
      "response": "Die Physik spricht eher für direkte Elektrifizierung. Im Pkw ist das Batterieauto deutlich effizienter als Wasserstoff oder E-Fuels. Diese Energieträger werden vor allem dort gebraucht, wo Batterien an Grenzen stoßen, etwa in Luftfahrt, Schifffahrt oder Teilen der Industrie.",
      "keywords": ["wasserstoff", "e-fuels", "brennstoffzelle", "zukunft", "brückentechnologie", "effizienz"],
      "relatedSections": ["efuels-wasserstoff"]
    },
    {
      "id": "brennende-autos",
      "claim": "E-Autos brennen ständig und können nicht gelöscht werden.",
      "response": "Die pauschale Behauptung stimmt nicht. Laut BMUKN brennen Elektroautos nicht häufiger als andere Fahrzeuge. Wenn ein Akku-Brand entsteht, ist das Löschen zwar aufwendiger, aber für Feuerwehren ist das ein bekanntes und beherrschbares Szenario.",
      "keywords": ["brennen", "feuer", "brandgefahr", "löschen", "feuerwehr", "explosion"],
      "relatedSections": ["brandgefahr"]
    },
    {
      "id": "reichweite",
      "claim": "Mit dem E-Auto komme ich nicht in den Urlaub nach Italien.",
      "response": "Auch längere Urlaubsfahrten sind mit E-Autos heute praktikabel. Das Schnellladenetz wächst weiter, und auf Langstrecken gehören Ladepausen ähnlich wie Tank- oder Ruhepausen ohnehin zur Reiseplanung dazu.",
      "keywords": ["urlaub", "reichweite", "italien", "langstrecke", "laden", "pause"],
      "relatedSections": ["status-quo"]
    }
  ],
  "sources": [
    {
      "label": "ICCT – Life-cycle GHG emissions of passenger cars (Juli 2025)",
      "url": "https://theicct.org/publication/electric-cars-life-cycle-analysis-emissions-europe-jul25/"
    },
    {
      "label": "ADAC – Autokostenrechner / TCO-Vergleich",
      "url": "https://www.adac.de/rund-ums-fahrzeug/auto-kaufen-verkaufen/autokosten/uebersicht/"
    },
    {
      "label": "BDEW – Marke von 200.000 Ladepunkten überschritten",
      "url": "https://www.bdew.de/presse/marke-von-200000-ladepunkten-ueberschritten-fokus-auf-elektrofahrzeugabsatz-kommt-zum-richtigen-zeitpunkt/"
    },
    {
      "label": "Bundesnetzagentur – E-Mobilität und § 14a EnWG",
      "url": "https://www.bundesnetzagentur.de/DE/Fachthemen/ElektrizitaetundGas/E-Mobilitaet/start.html"
    },
    {
      "label": "BMUKN – Klima und Energie bei Elektromobilität",
      "url": "https://www.bmuv.de/themen/verkehr/elektromobilitaet/klima-und-energie"
    },
    {
      "label": "Transport & Environment (T&E) – E-Fuels",
      "url": "https://www.transportenvironment.org/topics/cars/efuels"
    },
    {
      "label": "Fraunhofer ISI – Batterie-Recycling in Europa",
      "url": "https://www.isi.fraunhofer.de/de/blog/themen/batterie-update/batterie-recycling_europa_kapazitaeten_bedarf_update_2025.html"
    },
    {
      "label": "Kraftfahrt-Bundesamt (KBA) – Bestand batterieelektrischer Pkw am 1. Januar 2026",
      "url": "https://www.kba.de/DE/Presse/Pressemitteilungen/Allgemein/2026/pm08_2026_elektro_pkw.html"
    },
    {
      "label": "Kraftfahrt-Bundesamt (KBA) – Fahrzeugbestand am 1. Januar 2026",
      "url": "https://www.kba.de/DE/Presse/Pressemitteilungen/Fahrzeugbestand/2026/pm09_fz_bestand_pm_komplett.html"
    },
    {
      "label": "BMUKN – Brandgefahr von Elektroautos",
      "url": "https://www.bmuv.de/faq/wie-gefaehrlich-sind-elektroautos-besonders-im-fall-eines-brands"
    },
    {
      "label": "EU-Batterieverordnung 2023/1542 – Recyclingquoten",
      "url": "https://eur-lex.europa.eu/eli/reg/2023/1542/oj"
    },
    {
      "label": "Zoll – Verlängerung der Steuerbefreiung für reine Elektrofahrzeuge",
      "url": "https://www.zoll.de/SharedDocs/Fachmeldungen/Aktuelle-Einzelmeldungen/2026/kfz_verlaengerung_steuerbefreiung_elektrofahrzeuge.html"
    }
  ]
}
